mapqc/__init__.py
mapqc/_mapqc_scores.py
mapqc/_params.py
mapqc/_process_nhood.py
mapqc/evaluate.py
mapqc/run.py
mapqc/_center_cells/_sampling.py
mapqc/_distances/__init__.py
mapqc/_distances/_normalized_distances.py
mapqc/_distances/_raw_distances.py
mapqc/_neighbors/__init__.py
mapqc/_neighbors/_adaptive_k.py
mapqc/_neighbors/_filter.py
mapqc/_utils/__init__.py
mapqc/_utils/_validation.py
mapqc/pl/__init__.py
mapqc/pl/boxplot.py
mapqc/pl/umap.py
mapqc-0.1.1.dist-info/METADATA
mapqc-0.1.1.dist-info/WHEEL
mapqc-0.1.1.dist-info/licenses/LICENSE
mapqc-0.1.1.dist-info/RECORD
